openfermionblueqat/__init__.py
openfermionblueqat/_transform.py
openfermionblueqat/_version.py
openfermionblueqat/bk.py
openfermionblueqat/ucc.py
openfermionblueqat-0.2.2.dist-info/LICENSE
openfermionblueqat-0.2.2.dist-info/METADATA
openfermionblueqat-0.2.2.dist-info/WHEEL
openfermionblueqat-0.2.2.dist-info/top_level.txt
openfermionblueqat-0.2.2.dist-info/RECORD
